jautomate/__init__.py
jautomate/__main__.py
jautomate/actions.py
jautomate/api.py
jautomate/assets.py
jautomate/cli.py
jautomate/commands.py
jautomate/devices.py
jautomate/enums.py
jautomate/exceptions.py
jautomate/logger.py
jautomate/models.py
jautomate/utils.py
jautomate-0.0.23.dist-info/METADATA
jautomate-0.0.23.dist-info/WHEEL
jautomate-0.0.23.dist-info/entry_points.txt
jautomate-0.0.23.dist-info/top_level.txt
jautomate-0.0.23.dist-info/RECORD
