Metadata-Version: 2.1
Name: jautomate
Version: 0.0.23
Summary: Automates MDM tasks using the Jamf APIs
Author: Dustin Yoxall
Author-email: yoxall.dustin@ccpsstaff.org
License: MIT
Keywords: python,jamf
Classifier: Development Status :: 3 - Alpha
Classifier: Programming Language :: Python :: 3
Requires-Python: >=3.10
Requires-Dist: jps-api-wrapper
Requires-Dist: typer
Requires-Dist: python-dotenv
